LICENSE
MANIFEST.in
README.PyPI.md
README.md
requirements.txt
setup.py
doc/例子-1.png
doc/例子-2.png
doc/例子-3.png
doc/前缀树例子.png
doc/可视化.jpg
doc/稀疏表例子.png
doc/简化表示-1.png
doc/简化表示-2.png
sparse_lut/__init__.py
sparse_lut/branch_list.py
sparse_lut/demo.py
sparse_lut/sparse_lut.py
sparse_lut.egg-info/PKG-INFO
sparse_lut.egg-info/SOURCES.txt
sparse_lut.egg-info/dependency_links.txt
sparse_lut.egg-info/requires.txt
sparse_lut.egg-info/top_level.txt