Metadata-Version: 2.1
Name: sparse-lut
Version: 1.0.0
Summary: Sparse Look-Up-Table
Home-page: https://github.com/bowen-xu/SparseLUT
Author: Bowen XU
Author-email: xubowen@pku.edu.cn
License: MIT
Keywords: SparseLUT,Sparse,Look-Up Table
Platform: UNKNOWN
Classifier: Development Status :: 4 - Beta
Classifier: Intended Audience :: Developers
Classifier: License :: OSI Approved :: MIT License
Classifier: Natural Language :: English
Classifier: Natural Language :: Chinese (Simplified)
Classifier: Programming Language :: Python :: 3.7
Classifier: Programming Language :: Python :: 3.8
Classifier: Programming Language :: Python :: 3.9
Classifier: Programming Language :: Python :: 3.10
Requires-Python: >=3.7.0
License-File: LICENSE
